{
  "default_model": "BTC_4h",
  "models": {
    "ETH_USDT_1h": {
      "path": "models\\ETH_USDT_1h",
      "created_at": "2025-12-01T20:18:32.781666",
      "metadata_summary": {
        "symbols": [
          "ETH/USDT"
        ],
        "accuracy": null,
        "timeframe": "1h"
      }
    },
    "GENERAL_4h": {
      "path": "models\\GENERAL_4h",
      "created_at": "2025-12-01T21:50:33.470652",
      "metadata_summary": {
        "symbols": [
          "ETH/USDT",
          "SOL/USDT",
          "XRP/USDT",
          "ADA/USDT",
          "BNB/USDT"
        ],
        "accuracy": null,
        "timeframe": "1h"
      }
    },
    "GENERAL_4h_v2": {
      "path": "models\\GENERAL_4h_v2",
      "created_at": "2025-12-02T10:08:05.206462",
      "metadata_summary": {
        "symbols": [
          "ETH/USDT",
          "SOL/USDT",
          "XRP/USDT",
          "ADA/USDT",
          "BNB/USDT",
          "BTC/USDT",
          "DOGE/USDT"
        ],
        "accuracy": null,
        "timeframe": "1h"
      }
    },
    "SOL_4h_v1": {
      "path": "models\\SOL_4h_v1",
      "created_at": "2025-12-02T10:21:09.467301",
      "metadata_summary": {
        "symbols": [
          "SOL/USDT"
        ],
        "accuracy": null,
        "timeframe": "4h"
      }
    },
    "SOL_4h_optimized": {
      "path": "models\\SOL_4h_optimized",
      "created_at": "2025-12-02T10:28:26.495630",
      "metadata_summary": {
        "symbols": [
          "SOL/USDT"
        ],
        "accuracy": null,
        "timeframe": "4h"
      }
    },
    "SOL_4h_final": {
      "path": "models\\SOL_4h_final",
      "created_at": "2025-12-02T10:35:53.134803",
      "metadata_summary": {
        "symbols": [
          "SOL/USDT"
        ],
        "accuracy": null,
        "timeframe": "4h"
      }
    },
    "SOL_GROUP_4h": {
      "path": "models\\SOL_GROUP_4h",
      "created_at": "2025-12-02T11:08:09.574962",
      "metadata_summary": {
        "symbols": [
          "SOL/USDT",
          "AVAX/USDT",
          "MATIC/USDT",
          "DOGE/USDT"
        ],
        "accuracy": null,
        "timeframe": "4h"
      }
    },
    "BTC_4h": {
      "path": "models\\BTC_4h",
      "created_at": "2025-12-02T11:33:10.433849",
      "metadata_summary": {
        "symbols": [
          "BTC/USDT",
          "ETH/USDT"
        ],
        "accuracy": null,
        "timeframe": "4h"
      }
    },
    "BTC_4h_v2": {
      "path": "models\\BTC_4h_v2",
      "created_at": "2025-12-02T16:31:40.795551",
      "metadata_summary": {
        "symbols": [
          "BTC/USDT",
          "ETH/USDT"
        ],
        "accuracy": null,
        "timeframe": "4h"
      }
    },
    "ETH_4h_v2": {
      "path": "models\\ETH_4h_v2",
      "created_at": "2025-12-02T16:44:23.389367",
      "metadata_summary": {
        "symbols": [
          "ETH/USDT",
          "SOL/USDT",
          "XRP/USDT"
        ],
        "accuracy": null,
        "timeframe": "4h"
      }
    },
    "ETH_1h_v2": {
      "path": "models\\ETH_1h_v2",
      "created_at": "2025-12-02T17:09:33.862052",
      "metadata_summary": {
        "symbols": [
          "ETH/USDT",
          "SOL/USDT",
          "XRP/USDT"
        ],
        "accuracy": null,
        "timeframe": "1h"
      }
    },
    "BTC_4h_v3": {
      "path": "models\\BTC_4h_v3",
      "created_at": "2025-12-03T09:34:00.699374",
      "metadata_summary": {
        "symbols": [
          "BTC/USDT",
          "ETH/USDT"
        ],
        "accuracy": null,
        "timeframe": "4h"
      }
    },
    "BTC_1h_v2": {
      "path": "models\\BTC_1h_v2",
      "created_at": "2025-12-03T12:13:28.038823",
      "metadata_summary": {
        "symbols": [
          "BTC/USDT",
          "ETH/USDT"
        ],
        "accuracy": null,
        "timeframe": "1h"
      }
    },
    "SOL_1h_v2": {
      "path": "models\\SOL_1h_v2",
      "created_at": "2025-12-03T12:46:28.460222",
      "metadata_summary": {
        "symbols": [
          "SOL/USDT",
          "AVAX/USDT",
          "MATIC/USDT",
          "DOGE/USDT"
        ],
        "accuracy": null,
        "timeframe": "1h"
      }
    },
    "GENERAL_GROUP_1h_v2": {
      "path": "models\\GENERAL_GROUP_1h_v2",
      "created_at": "2025-12-03T13:43:19.266097",
      "metadata_summary": {
        "symbols": [
          "SOL/USDT",
          "ETH/USDT",
          "XRP/USDT",
          "SOL/EUR",
          "ETH/EUR",
          "BTC/USDT",
          "BTC/EUR",
          "DOGE/USDT",
          "DOGE/EUR"
        ],
        "accuracy": null,
        "timeframe": "1h"
      }
    },
    "BTC_1h_v4": {
      "path": "models\\BTC_1h_v4",
      "created_at": "2025-12-03T20:28:25.588934",
      "metadata_summary": {
        "symbols": [
          "BTC/USDT"
        ],
        "accuracy": null,
        "timeframe": "1h"
      }
    },
    "BTC_4h_v4": {
      "path": "models\\BTC_4h_v4",
      "created_at": "2025-12-05T09:00:05.061557",
      "metadata_summary": {
        "symbols": [
          "ETH/USDT",
          "BTC/USDT",
          "SOL/USDT",
          "XRP/USDT",
          "ADA/USDT",
          "DOGE/USDT",
          "LINK/USDT",
          "BNB/USDT"
        ],
        "accuracy": null,
        "timeframe": "4h"
      }
    },
    "BTC_4h_v5": {
      "path": "models\\BTC_4h_v5",
      "created_at": "2025-12-05T10:18:47.377953",
      "metadata_summary": {
        "symbols": [
          "ETH/USDT",
          "BTC/USDT",
          "SOL/USDT",
          "XRP/USDT",
          "ADA/USDT",
          "DOGE/USDT",
          "LINK/USDT",
          "BNB/USDT"
        ],
        "accuracy": null,
        "timeframe": "4h"
      }
    },
    "BTC_4h_v6": {
      "path": "models\\BTC_4h_v6",
      "created_at": "2025-12-05T12:10:51.033277",
      "metadata_summary": {
        "symbols": [
          "ETH/USDT",
          "BTC/USDT",
          "SOL/USDT",
          "XRP/USDT",
          "ADA/USDT",
          "DOGE/USDT",
          "LINK/USDT",
          "BNB/USDT"
        ],
        "accuracy": null,
        "timeframe": "4h"
      }
    },
    "BTC_4h_v7": {
      "path": "models\\BTC_4h_v7",
      "created_at": "2025-12-05T16:30:55.727208",
      "metadata_summary": {
        "symbols": [
          "ETH/USDT",
          "BTC/USDT",
          "SOL/USDT",
          "XRP/USDT",
          "ADA/USDT",
          "DOGE/USDT",
          "LINK/USDT",
          "BNB/USDT"
        ],
        "accuracy": null,
        "timeframe": "4h"
      }
    },
    "BTC_4h_v8": {
      "path": "models\\BTC_4h_v8",
      "created_at": "2025-12-06T03:14:17.997495",
      "metadata_summary": {
        "symbols": [
          "ETH/USDT",
          "BTC/USDT",
          "SOL/USDT",
          "XRP/USDT",
          "ADA/USDT",
          "DOGE/USDT",
          "LINK/USDT",
          "BNB/USDT"
        ],
        "accuracy": null,
        "timeframe": "4h"
      }
    }
  }
}